counter.v
module counter(
    input clk,
    output reg [3:0] q
);

initial q = 0;

always @(posedge clk)
    q <= q + 1;

endmodule

counter_tb.v
module counter_tb;

reg clk;
wire [3:0] q;

counter uut(
    .clk(clk),
    .q(q)
);

initial begin
    clk = 0;
    #100 $finish;
end

always #5 clk = ~clk;

initial begin
    $dumpfile("counter.vcd");
    $dumpvars(0);
end

endmodule

counter.vcd
$date
	Tue Jun 02 12:01:25 2026
$end
$version
	Icarus Verilog
$end
$timescale
	1s
$end
$scope module counter_tb $end
$var wire 4 ! q [3:0] $end
$var reg 1 " clk $end
$scope module uut $end
$var wire 1 " clk $end
$var reg 4 # q [3:0] $end
$upscope $end
$upscope $end
$enddefinitions $end
$comment Show the parameter values. $end
$dumpall
$end
#0
$dumpvars
b0 #
0"
b0 !
$end
#5
b1 !
b1 #
1"
#10
0"
#15
b10 !
b10 #
1"
#20
0"
#25
b11 !
b11 #
1"
#30
0"
#35
b100 !
b100 #
1"
#40
0"
#45
b101 !
b101 #
1"
#50
0"
#55
b110 !
b110 #
1"
#60
0"
#65
b111 !
b111 #
1"
#70
0"
#75
b1000 !
b1000 #
1"
#80
0"
#85
b1001 !
b1001 #
1"
#90
0"
#95
b1010 !
b1010 #
1"
